{"peut": 0, "rouge": 1, "vertes": 2, "plus": 3, "est": 4, "Quelle": 5, "se": 6, "etoile": 7, "trouve": 8, "gauche": 9, "Qu": 10, "bleu": 11, "blanche": 12, "droite": 13, "haut": 14, "blanches": 15, "rectangles": 16, "voir": 17, "qu": 18, "au": 19, "de": 20, "figure": 21, "vert": 22, "?": 23, "ellipses": 24, "bas": 25, "rouges": 26, "bleus": 27, "que": 28, "verte": 29, "figures": 30, "blancs": 31, "Est": 32, "d": 33, "en": 34, "nombre": 35, "on": 36, "Que": 37, "Quel": 38, "centre": 39, "Peut": 40, "bleues": 41, "observer": 42, "Y": 43, "t": 44, "triangle": 45, "verts": 46, "rectangle": 47, "il": 48, "bleue": 49, "y": 50, "le": 51, "ce": 52, "ellipse": 53, "Combien": 54, "triangles": 55, "etoiles": 56, "des": 57, "blanc": 58, "a": 59}